Metadata-Version: 1.0
Name: oversee
Version: 0.22
Summary: A python utility to help manage your Ubuntu OS!
Home-page: http://github.com/jacsmith21/oversee
Author: Jacob Smith
Author-email: jacob.smith@unb.ca
License: UNKNOWN
Platform: UNKNOWN
